tb_wrapper/AlarmController.py
tb_wrapper/AssetController.py
tb_wrapper/Connection.py
tb_wrapper/DeviceController.py
tb_wrapper/MainController.py
tb_wrapper/QueryController.py
tb_wrapper/TelemetryController.py
tb_wrapper/UserController.py
tb_wrapper/__init__.py
tb_wrapper/handle_exception.py
tb_wrapper-0.1.28.dist-info/LICENSE
tb_wrapper-0.1.28.dist-info/METADATA
tb_wrapper-0.1.28.dist-info/WHEEL
tb_wrapper-0.1.28.dist-info/top_level.txt
tb_wrapper-0.1.28.dist-info/RECORD
