Metadata-Version: 2.1
Name: tb_wrapper
Version: 0.1.28
Summary: Wrapper for Zoe Project
Author-email: GolDAndy <author@example.com>
Project-URL: Homepage, https://github.com/GolDandy7/tb_wrapper
Classifier: Programming Language :: Python :: 3
Classifier: License :: OSI Approved :: MIT License
Classifier: Operating System :: OS Independent
Requires-Python: >=3.8
License-File: LICENSE
Requires-Dist: tb-rest-client >=3.5
Requires-Dist: requests >=2.28
Requires-Dist: jwt
Requires-Dist: six >=1.16
